.travis.yml
LICENSE.txt
MANIFEST.in
README.rst
setup.py
tox.ini
Flask_ToyBox.egg-info/PKG-INFO
Flask_ToyBox.egg-info/SOURCES.txt
Flask_ToyBox.egg-info/dependency_links.txt
Flask_ToyBox.egg-info/not-zip-safe
Flask_ToyBox.egg-info/requires.txt
Flask_ToyBox.egg-info/top_level.txt
example/LICENSE.txt
example/README.rst
example/example.py
example/requirements.txt
example/example/__init__.py
example/example/auth.py
example/example/models.py
example/example/settings.py
example/example/utils.py
example/example/views.py
flask_toybox/__init__.py
flask_toybox/compat.py
flask_toybox/etags.py
flask_toybox/exceptions.py
flask_toybox/permissions.py
flask_toybox/serialization.py
flask_toybox/sqlalchemy.py
flask_toybox/utils.py
flask_toybox/views.py
tests/__init__.py
tests/__init__.pyc
tests/test_model.py
tests/test_model.pyc
tests/test_negotiation.py
tests/test_negotiation.pyc
tests/test_serialization.py
tests/test_serialization.pyc
tests/test_sqlalchemy.py
tests/test_sqlalchemy.pyc