Metadata-Version: 1.1
Name: Flask-ToyBox
Version: 0.0.3
Summary: Create somehow-RESTful HTTP APIs with Flask
Home-page: https://github.com/drdaeman/flask-toybox/
Author: Aleksey Zhukov
Author-email: drdaeman@drdaeman.pp.ru
License: MIT
Platform: any
Classifier: Development Status :: 2 - Pre-Alpha
Classifier: Environment :: Web Environment
Classifier: Topic :: Internet :: WWW/HTTP :: Dynamic Content
Classifier: Intended Audience :: Developers
Classifier: Operating System :: OS Independent
Classifier: License :: OSI Approved :: MIT License
Classifier: Programming Language :: Python
Classifier: Programming Language :: Python :: 2.7
Classifier: Programming Language :: Python :: 2 :: Only
Classifier: Topic :: Software Development :: Libraries :: Python Modules
